py_configorm/__init__.py
py_configorm/core.py
py_configorm/exception.py
py_configorm/sources/__init__.py
py_configorm/sources/base.py
py_configorm/sources/dotenv_source.py
py_configorm/sources/env_source.py
py_configorm/sources/json_source.py
py_configorm/sources/toml_source.py
py_configorm/sources/yaml_source.py
py_configorm/validators/__init__.py
py_configorm/validators/schema.py
py_configorm-0.1.1.dist-info/METADATA
py_configorm-0.1.1.dist-info/WHEEL
py_configorm-0.1.1.dist-info/RECORD
